dash_pager/Pager.py
dash_pager/__init__.py
dash_pager/_imports_.py
dash_pager/async-Pager.js
dash_pager/async-Pager.js.map
dash_pager/dash_pager.min.js
dash_pager/dash_pager.min.js.map
dash_pager/metadata.json
dash_pager/package-info.json
dash_pager-0.1.5.dist-info/LICENSE
dash_pager-0.1.5.dist-info/METADATA
dash_pager-0.1.5.dist-info/WHEEL
dash_pager-0.1.5.dist-info/top_level.txt
dash_pager-0.1.5.dist-info/RECORD
