Metadata-Version: 2.1
Name: dash_pager
Version: 0.1.5
Summary: Generic pagination component for dash and dash bootstrap components
Author: Tarlis Portela <tarlis@tarlis.com.br>
License: GPL-3.0
Classifier: Framework :: Dash
License-File: LICENSE
